Metadata-Version: 2.1
Name: vadim2304-MyProject
Version: 1.0
Summary: project
Home-page: https://www.google.com.ua/
Author: Vadim
Author-email: vadkl87@gmail.com
License: UNKNOWN
Platform: UNKNOWN
